pytest_dbfixtures-0.13.1.dist-info/METADATA
pytest_dbfixtures-0.13.1.dist-info/DESCRIPTION.rst
pytest_dbfixtures-0.13.1.dist-info/metadata.json
pytest_dbfixtures-0.13.1.dist-info/RECORD
pytest_dbfixtures-0.13.1.dist-info/entry_points.txt
pytest_dbfixtures-0.13.1.dist-info/top_level.txt
pytest_dbfixtures-0.13.1.dist-info/WHEEL
pytest_dbfixtures/plugin.py
pytest_dbfixtures/port.py
pytest_dbfixtures/__init__.py
pytest_dbfixtures/utils.py
pytest_dbfixtures/conf/rabbit.conf
pytest_dbfixtures/conf/redis.conf
pytest_dbfixtures/conf/dbfixtures.conf
pytest_dbfixtures/factories/rabbitmq.py
pytest_dbfixtures/factories/mysql.py
pytest_dbfixtures/factories/mongo.py
pytest_dbfixtures/factories/postgresql.py
pytest_dbfixtures/factories/redis.py
pytest_dbfixtures/factories/__init__.py
pytest_dbfixtures/factories/elasticsearch.py
pytest_dbfixtures/factories/rabbitmq_client.py
pytest_dbfixtures/factories/mysql_client.py
pytest_dbfixtures/executors/extensions.py
pytest_dbfixtures/executors/postgresql.py
pytest_dbfixtures/executors/__init__.py
