Metadata-Version: 2.0
Name: pytest-dbfixtures
Version: 0.13.1
Summary: Databases fixtures plugin for py.test.
Home-page: https://github.com/ClearcodeHQ/pytest-dbfixtures
Author: Clearcode - The A Room
Author-email: thearoom@clearcode.cc
License: UNKNOWN
Keywords: tests py.test pytest fixture redis mongo mongodb rabbit rabbitmq mysql postgres postgresql elasticsearch
Platform: UNKNOWN
Classifier: Development Status :: 4 - Beta
Classifier: Intended Audience :: Developers
Classifier: Operating System :: POSIX
Classifier: Operating System :: MacOS :: MacOS X
Classifier: Topic :: Software Development :: Quality Assurance
Classifier: Topic :: Software Development :: Testing
Classifier: Topic :: Utilities
Classifier: Programming Language :: Python
Classifier: Programming Language :: Python :: 2
Classifier: Programming Language :: Python :: 2.7
Classifier: Programming Language :: Python :: 3
Classifier: Programming Language :: Python :: 3.3
Classifier: Programming Language :: Python :: 3.4
Classifier: Programming Language :: Python :: 3.5
Requires-Dist: pytest (>=2.3.4)
Requires-Dist: mirakuru (>=0.2)
Requires-Dist: pyaml (>=3.10)
Requires-Dist: pymlconf (>=0.2.10a,!=0.3.12,!=0.3.13,!=0.3.14)
Requires-Dist: path.py (>=4.2)
Requires-Dist: port-for (>=0.3.1)
Provides-Extra: deploy
Requires-Dist: bumpversion; extra == 'deploy'
Provides-Extra: documentation
Requires-Dist: Sphinx; extra == 'documentation'
Provides-Extra: elasticsearch
Requires-Dist: elasticsearch; extra == 'elasticsearch'
Provides-Extra: mongodb
Requires-Dist: pymongo; extra == 'mongodb'
Provides-Extra: mysql
Requires-Dist: mysqlclient; extra == 'mysql'
Provides-Extra: postgresql
Requires-Dist: psycopg2; extra == 'postgresql'
Provides-Extra: rabbitmq
Requires-Dist: rabbitpy; extra == 'rabbitmq'
Provides-Extra: redis
Requires-Dist: redis; extra == 'redis'
Provides-Extra: tests
Requires-Dist: pytest-cov; extra == 'tests'
Requires-Dist: pytest-xdist; extra == 'tests'
Requires-Dist: coveralls; extra == 'tests'
Requires-Dist: pylama; extra == 'tests'
Requires-Dist: Mock; extra == 'tests'
